LICENSE
MANIFEST.in
README.md
setup.py
gropen/__init__.py
gropen/__main__.py
gropen/gropen.py
gropen.egg-info/PKG-INFO
gropen.egg-info/SOURCES.txt
gropen.egg-info/dependency_links.txt
gropen.egg-info/entry_points.txt
gropen.egg-info/top_level.txt
tests/__init__.py
tests/test_gropen.py