Metadata-Version: 2.1
Name: gropen
Version: 0.3.0
Summary: CLI for opening local files on browsers based on a remote git repository
Home-page: https://github.com/tiagopog/gropen/
Author: Tiago Guedes
Author-email: tiagopog@gmail.com
License: UNKNOWN
Project-URL: Bug Tracker, https://github.com/tiagopog/gropen/issues
Platform: UNKNOWN
Classifier: Intended Audience :: Developers
Classifier: License :: OSI Approved :: MIT License
Classifier: Operating System :: Unix
Classifier: Programming Language :: Python :: 3
Classifier: Topic :: Software Development
Classifier: Topic :: Software Development :: Libraries :: Python Modules
Requires-Python: >=3.6
